{
    "PlayerCache": [
        {"Name": "horrid", "Planet": "dantooine", "Timestamp": 1698363568544, "X": -4203.7, "Y": -2350.84, "Id": 281474995078523},
        {"Name": "lucille", "Planet": "naboo", "Timestamp": 1697718801271, "X": -5162.87, "Y": 4289.45, "Id": 281474995078545},
        {"Name": "jonas", "Planet": "corellia", "Timestamp": 1697202533791, "X": -64.12, "Y": -4712.76, "Id": 281474995078958},
        {"Name": "zyrain", "Planet": "dantooine", "Timestamp": 1697864746564, "X": 1042.1, "Y": -663.21, "Id": 281474995080528},
        {"Name": "efrin ceiye", "Planet": "naboo", "Timestamp": 1698070399396, "X": -4888.0, "Y": 4184.95, "Id": 281474995080555},
        {"Name": "touched", "Planet": "naboo", "Timestamp": 1697156142820, "X": -5163.45, "Y": 4290.99, "Id": 281474995081146},
        {"Name": "ifrin saibin", "Planet": "naboo", "Timestamp": 1697293578451, "X": -4993.36, "Y": 4165.88, "Id": 281474995086278},
        {"Name": "warstoned", "Planet": "rori", "Timestamp": 1697243246882, "X": 757.22, "Y": -4704.43, "Id": 281474995086391},
        {"Name": "hein sole", "Planet": "naboo", "Timestamp": 1697281501430, "X": 5277.21, "Y": 6687.76, "Id": 281474995087946},
        {"Name": "pete walker", "Planet": "endor", "Timestamp": 1697260010764, "X": -947.17, "Y": 1555.48, "Id": 281474995090803},
        {"Name": "lucian", "Planet": "naboo", "Timestamp": 1697242983413, "X": -5083.61, "Y": 4194.7, "Id": 281474995100388},
        {"Name": "ihatecrafting", "Planet": "lok", "Timestamp": 1697318317769, "X": 476.4, "Y": 5515.05, "Id": 281474995107147},
        {"Name": "manny fingers", "Planet": "corellia", "Timestamp": 1697199032866, "X": -62.72, "Y": -4708.38, "Id": 281474995114773},
        {"Name": "yaniths apprentice", "Planet": "endor", "Timestamp": 1697911442340, "X": -954.46, "Y": 1556.58, "Id": 281474995116562},
        {"Name": "luke", "Planet": "naboo", "Timestamp": 1697419949229, "X": -5160.97, "Y": 4291.04, "Id": 281474995116671},
        {"Name": "slappy", "Planet": "naboo", "Timestamp": 1697294943012, "X": 5275.32, "Y": 6684.56, "Id": 281474995120382},
        {"Name": "pappy", "Planet": "naboo", "Timestamp": 1697299653765, "X": 5356.81, "Y": 6579.83, "Id": 281474995128089},
        {"Name": "oppenheimer", "Planet": "dantooine", "Timestamp": 1697534493204, "X": 1004.36, "Y": -683.44, "Id": 281474995142271},
        {"Name": "arnold schwarzenegger", "Planet": "naboo", "Timestamp": 1698014272990, "X": -5008.37, "Y": 4201.26, "Id": 281474995171644},
        {"Name": "sylvester stallone", "Planet": "naboo", "Timestamp": 1698149440734, "X": -5162.05, "Y": 4292.23, "Id": 281474995193949},
        {"Name": "harvester", "Planet": "dantooine", "Timestamp": 1698360942143, "X": -634.28, "Y": 2493.13, "Id": 281474995254592},
        {"Name": "llllllll", "Planet": "corellia", "Timestamp": 1697198537761, "X": -65.88, "Y": -4716.25, "Id": 281474995349214},
        {"Name": "carri", "Planet": "dantooine", "Timestamp": 1698097172509, "X": 1045.96, "Y": -659.7, "Id": 281474995463553},
        {"Name": "raja zola", "Planet": "dantooine", "Timestamp": 1697833636561, "X": 1043.59, "Y": -694.38, "Id": 281474995485471},
        {"Name": "candy", "Planet": "dantooine", "Timestamp": 1697587235860, "X": 1043.18, "Y": -659.48, "Id": 281474995494762},
        {"Name": "wubbafett", "Planet": "naboo", "Timestamp": 1697537468721, "X": -5164.16, "Y": 4291.41, "Id": 281474995758871},
        {"Name": "awesome sauce", "Planet": "naboo", "Timestamp": 1697246679495, "X": 5306.01, "Y": 6674.85, "Id": 281474996028433},
        {"Name": "ahsoka tano", "Planet": "naboo", "Timestamp": 1697156142820, "X": -5150.79, "Y": 4275.59, "Id": 281474996072529},
        {"Name": "miz stress", "Planet": "dantooine", "Timestamp": 1698277782046, "X": -640.66, "Y": 2505.27, "Id": 281474996224321},
        {"Name": "princi", "Planet": "rori", "Timestamp": 1697279959473, "X": 3682.33, "Y": -6456.24, "Id": 281474996295639},
        {"Name": "meso hungry", "Planet": "naboo", "Timestamp": 1697418598412, "X": -5005.46, "Y": 4243.08, "Id": 281474996308733},
        {"Name": "amazing sauce", "Planet": "naboo", "Timestamp": 1697249118001, "X": 5150.73, "Y": 6639.93, "Id": 281474996584781},
        {"Name": "martha stewart", "Planet": "corellia", "Timestamp": 1697197352119, "X": 122.05, "Y": -4755.88, "Id": 281474996628070},
        {"Name": "herman thegerman", "Planet": "naboo", "Timestamp": 1697293578451, "X": -4994.22, "Y": 4165.21, "Id": 281474996735740},
        {"Name": "hecate", "Planet": "naboo", "Timestamp": 1698350811169, "X": -5154.93, "Y": 4295.3, "Id": 281474996804175},
        {"Name": "jangle lang", "Planet": "rori", "Timestamp": 1697832576571, "X": -5378.05, "Y": -2189.0, "Id": 281474996889882},
        {"Name": "bia phish", "Planet": "dantooine", "Timestamp": 1697587235860, "X": 1045.65, "Y": -693.2, "Id": 281474997271742},
        {"Name": "numbers", "Planet": "naboo", "Timestamp": 1698247203061, "X": -5003.55, "Y": 4220.31, "Id": 281474997515221},
        {"Name": "hythos", "Planet": "naboo", "Timestamp": 1698351379853, "X": -5135.29, "Y": 3720.65, "Id": 281474997590174},
        {"Name": "armordala queen", "Planet": "naboo", "Timestamp": 1697503976600, "X": -4654.37, "Y": 3160.21, "Id": 281474997808728},
        {"Name": "brianna", "Planet": "corellia", "Timestamp": 1697199034661, "X": 95.03, "Y": -4820.85, "Id": 281474997875078},
        {"Name": "shawn michaels", "Planet": "corellia", "Timestamp": 1697974932655, "X": -3869.42, "Y": 2368.74, "Id": 281474998204873},
        {"Name": "sekoor", "Planet": "naboo", "Timestamp": 1698249106390, "X": -4888.55, "Y": 3906.87, "Id": 281474998261426},
        {"Name": "sexy ifrin", "Planet": "naboo", "Timestamp": 1697408170664, "X": -4994.36, "Y": 4161.86, "Id": 281474998524801},
        {"Name": "the smith", "Planet": "corellia", "Timestamp": 1698081019880, "X": -55.11, "Y": -4533.64, "Id": 281474999505939},
        {"Name": "flyin tortilla", "Planet": "corellia", "Timestamp": 1697200564796, "X": -70.27, "Y": -4713.25, "Id": 281474999532527},
        {"Name": "burl", "Planet": "dantooine", "Timestamp": 1697835358147, "X": 894.48, "Y": -728.52, "Id": 281474999767804},
        {"Name": "fazer", "Planet": "naboo", "Timestamp": 1697332571820, "X": 5121.84, "Y": 6611.27, "Id": 281475001016619},
        {"Name": "diggerdoug", "Planet": "naboo", "Timestamp": 1697280783059, "X": 6746.27, "Y": 3550.22, "Id": 281475001123842},
        {"Name": "myso hungry", "Planet": "dantooine", "Timestamp": 1698251450754, "X": -2923.0, "Y": -2156.0, "Id": 281475001443969},
        {"Name": "diggerdave", "Planet": "naboo", "Timestamp": 1697280783261, "X": 6746.4, "Y": 3548.62, "Id": 281475001452576},
        {"Name": "poopinin thestreets", "Planet": "naboo", "Timestamp": 1697205104409, "X": -4856.22, "Y": 4169.17, "Id": 281475002034843},
        {"Name": "apu nahasapeemapetilon", "Planet": "naboo", "Timestamp": 1697205104409, "X": -4862.66, "Y": 4165.93, "Id": 281475002067934},
        {"Name": "colorman sky", "Planet": "corellia", "Timestamp": 1697204070156, "X": -68.44, "Y": -4714.96, "Id": 281475002782594},
        {"Name": "cringe", "Planet": "corellia", "Timestamp": 1698021376596, "X": -3186.26, "Y": 2793.25, "Id": 281475004899948},
        {"Name": "perfect a-f", "Planet": "corellia", "Timestamp": 1697904857510, "X": -3152.33, "Y": 2876.9, "Id": 281475005062042},
        {"Name": "kain dren", "Planet": "endor", "Timestamp": 1697334858589, "X": -906.24, "Y": 1609.52, "Id": 281475005310958},
        {"Name": "eddievan halen", "Planet": "naboo", "Timestamp": 1697248090920, "X": 5280.66, "Y": 6683.07, "Id": 281475006030241},
        {"Name": "chodie juan'kenobi", "Planet": "dantooine", "Timestamp": 1698360015470, "X": 6306.37, "Y": -4170.39, "Id": 281475006311471},
        {"Name": "kallie", "Planet": "dantooine", "Timestamp": 1697534493204, "X": 1043.35, "Y": -657.2, "Id": 281475006930303},
        {"Name": "morrigan", "Planet": "dantooine", "Timestamp": 1697534493204, "X": 1045.12, "Y": -657.16, "Id": 281475006952416},
        {"Name": "wonk febuli", "Planet": "rori", "Timestamp": 1697680277294, "X": 3672.61, "Y": -6438.78, "Id": 281475007143085},
        {"Name": "heisenberg", "Planet": "dantooine", "Timestamp": 1698363617541, "X": 1944.46, "Y": -1633.6, "Id": 281475007748778},
        {"Name": "dantarishake mokkpie", "Planet": "corellia", "Timestamp": 1697200204983, "X": -68.4, "Y": -4706.6, "Id": 281475007825188},
        {"Name": "achey breaky", "Planet": "rori", "Timestamp": 1697681583112, "X": 3842.56, "Y": -6382.09, "Id": 281475008142978},
        {"Name": "sensai", "Planet": "naboo", "Timestamp": 1697584791589, "X": -4506.69, "Y": 3152.01, "Id": 281475008214637},
        {"Name": "mitty", "Planet": "naboo", "Timestamp": 1697907643602, "X": -5165.0, "Y": 4287.11, "Id": 281475008264480},
        {"Name": "nurse ratched", "Planet": "dantooine", "Timestamp": 1697833636561, "X": 1197.43, "Y": -707.32, "Id": 281475008574529},
        {"Name": "fappy", "Planet": "dantooine", "Timestamp": 1697833636561, "X": 1040.32, "Y": -658.2, "Id": 281475008657088},
        {"Name": "bark", "Planet": "naboo", "Timestamp": 1697280783328, "X": 6746.48, "Y": 3549.53, "Id": 281475008815925},
        {"Name": "corbantis bark", "Planet": "naboo", "Timestamp": 1697280783328, "X": 6746.33, "Y": 3546.61, "Id": 281475009023712},
        {"Name": "arxow", "Planet": "corellia", "Timestamp": 1697196871719, "X": -62.93, "Y": -4712.48, "Id": 281475010011733},
        {"Name": "sylvari funbags", "Planet": "naboo", "Timestamp": 1698107482804, "X": -5160.98, "Y": 4292.47, "Id": 281475010318360},
        {"Name": "ravennah nightshade", "Planet": "naboo", "Timestamp": 1697320106065, "X": 5283.09, "Y": 6693.31, "Id": 281475011301977},
        {"Name": "syndara storm", "Planet": "naboo", "Timestamp": 1697243437992, "X": 5284.78, "Y": 6686.05, "Id": 281475011317547},
        {"Name": "falke-", "Planet": "naboo", "Timestamp": 1697280745101, "X": 7301.81, "Y": 3684.38, "Id": 281475014483627},
        {"Name": "preacher", "Planet": "naboo", "Timestamp": 1697858943847, "X": -4932.32, "Y": 4151.43, "Id": 281475014703400},
        {"Name": "listarchos devious", "Planet": "naboo", "Timestamp": 1698107664809, "X": -5000.11, "Y": 4238.12, "Id": 281475015860277},
        {"Name": "shaddos devious", "Planet": "naboo", "Timestamp": 1698279817016, "X": -4866.32, "Y": 4183.03, "Id": 281475016266464},
        {"Name": "shmoopie", "Planet": "naboo", "Timestamp": 1698080682496, "X": -4854.28, "Y": 4165.46, "Id": 281475017099251},
        {"Name": "exxod", "Planet": "dantooine", "Timestamp": 1697908009307, "X": 980.06, "Y": -683.06, "Id": 281475017827991},
        {"Name": "starkiller", "Planet": "naboo", "Timestamp": 1697242983413, "X": -4983.84, "Y": 4170.04, "Id": 281475017949866},
        {"Name": "jromac", "Planet": "rori", "Timestamp": 1697579665603, "X": 3662.29, "Y": -6429.08, "Id": 281475018103379},
        {"Name": "sesmu", "Planet": "naboo", "Timestamp": 1697318935630, "X": 5283.7, "Y": 6692.93, "Id": 281475020471780},
        {"Name": "macjro", "Planet": "dantooine", "Timestamp": 1698185345478, "X": -4275.41, "Y": -2400.17, "Id": 281475021317978},
        {"Name": "mom zukka", "Planet": "corellia", "Timestamp": 1697197864968, "X": -64.85, "Y": -4717.02, "Id": 281475021827143},
        {"Name": "zibba", "Planet": "naboo", "Timestamp": 1697459108982, "X": -5157.87, "Y": 4293.26, "Id": 281475021916008},
        {"Name": "exodia", "Planet": "dantooine", "Timestamp": 1697534493204, "X": 1009.6, "Y": -696.86, "Id": 281475022104394},
        {"Name": "mazzia", "Planet": "naboo", "Timestamp": 1697644870088, "X": -4855.4, "Y": 4159.15, "Id": 281475023574834},
        {"Name": "elder", "Planet": "rori", "Timestamp": 1697279978707, "X": 3521.72, "Y": -6356.3, "Id": 281475024020317},
        {"Name": "bodax", "Planet": "corellia", "Timestamp": 1697200820092, "X": -67.09, "Y": -4715.31, "Id": 281475024142926},
        {"Name": "bendras ovva", "Planet": "naboo", "Timestamp": 1697749130979, "X": -5014.14, "Y": 4152.62, "Id": 281475024648147},
        {"Name": "beamando", "Planet": "dantooine", "Timestamp": 1698249461580, "X": 572.46, "Y": -1649.93, "Id": 281475024792019},
        {"Name": "smako", "Planet": "naboo", "Timestamp": 1697242297910, "X": 5163.78, "Y": 6503.81, "Id": 281475024830326},
        {"Name": "frank's mustache", "Planet": "dantooine", "Timestamp": 1697833646898, "X": 897.85, "Y": -835.33, "Id": 281475025770628},
        {"Name": "doug dimmadome", "Planet": "naboo", "Timestamp": 1697896734000, "X": -5013.05, "Y": 4249.53, "Id": 281475026723712},
        {"Name": "teru", "Planet": "dantooine", "Timestamp": 1697833636561, "X": 1045.23, "Y": -696.04, "Id": 281475026851202},
        {"Name": "spus", "Planet": "lok", "Timestamp": 1697316722878, "X": 470.94, "Y": 5511.77, "Id": 281475026900419},
        {"Name": "maeve", "Planet": "dantooine", "Timestamp": 1697534493205, "X": 1041.82, "Y": -662.65, "Id": 281475026927456},
        {"Name": "lofwarr", "Planet": "dantooine", "Timestamp": 1698108452293, "X": 6313.5, "Y": -4173.81, "Id": 281475028698485},
        {"Name": "mallacuk", "Planet": "corellia", "Timestamp": 1698097042334, "X": -69.37, "Y": -4708.3, "Id": 281475029051695},
        {"Name": "turok", "Planet": "naboo", "Timestamp": 1698279566531, "X": -5004.24, "Y": 4215.27, "Id": 281475029940168},
        {"Name": "adorah bol", "Planet": "naboo", "Timestamp": 1697418598412, "X": -5003.15, "Y": 4138.2, "Id": 281475030143436},
        {"Name": "wipaetho", "Planet": "naboo", "Timestamp": 1697156142820, "X": -5158.78, "Y": 4289.99, "Id": 281475030241839},
        {"Name": "kathryn janeway", "Planet": "naboo", "Timestamp": 1698249111296, "X": -4942.69, "Y": 3874.66, "Id": 281475030510255},
        {"Name": "xasha vizsla", "Planet": "naboo", "Timestamp": 1697156142820, "X": -5163.05, "Y": 4291.88, "Id": 281475030661932},
        {"Name": "odd job", "Planet": "naboo", "Timestamp": 1697669977431, "X": -4859.62, "Y": 4170.53, "Id": 281475031199572},
        {"Name": "sup", "Planet": "naboo", "Timestamp": 1697280193170, "X": -4856.55, "Y": 4160.79, "Id": 281475032661422},
        {"Name": "samples", "Planet": "naboo", "Timestamp": 1697853460422, "X": 5278.82, "Y": 6690.71, "Id": 281475032675895},
        {"Name": "pills", "Planet": "naboo", "Timestamp": 1697156142820, "X": -5163.1, "Y": 4289.55, "Id": 281475032701088},
        {"Name": "blazinraider", "Planet": "naboo", "Timestamp": 1697418668676, "X": -5162.5, "Y": 4294.66, "Id": 281475033026399},
        {"Name": "putt ski", "Planet": "naboo", "Timestamp": 1697585599128, "X": -5123.56, "Y": 4205.25, "Id": 281475033061001},
        {"Name": "mistey morning", "Planet": "naboo", "Timestamp": 1697408914679, "X": -4879.34, "Y": 4156.02, "Id": 281475033083118},
        {"Name": "arsinoe", "Planet": "naboo", "Timestamp": 1697839685280, "X": 5283.48, "Y": 6685.76, "Id": 281475033668381},
        {"Name": "mia dawn", "Planet": "naboo", "Timestamp": 1698249097371, "X": -4834.16, "Y": 3813.97, "Id": 281475034077243},
        {"Name": "feta", "Planet": "naboo", "Timestamp": 1697980106057, "X": -5149.54, "Y": 4271.55, "Id": 281475034211825},
        {"Name": "muenster", "Planet": "naboo", "Timestamp": 1697681598033, "X": -5020.64, "Y": 4182.69, "Id": 281475034277704},
        {"Name": "mysterious stranger", "Planet": "naboo", "Timestamp": 1697280654591, "X": -5059.98, "Y": 3968.27, "Id": 281475034289083},
        {"Name": "closely", "Planet": "naboo", "Timestamp": 1697408185019, "X": -5162.62, "Y": 4292.59, "Id": 281475034724726},
        {"Name": "san holo", "Planet": "corellia", "Timestamp": 1697898287950, "X": -3179.8, "Y": 2930.86, "Id": 281475034916677},
        {"Name": "tieger", "Planet": "corellia", "Timestamp": 1697197885161, "X": -70.55, "Y": -4712.62, "Id": 281475035303061},
        {"Name": "maxinae", "Planet": "naboo", "Timestamp": 1697418624574, "X": -4853.83, "Y": 4160.76, "Id": 281475035333297},
        {"Name": "souldigger", "Planet": "naboo", "Timestamp": 1697418598412, "X": -5162.24, "Y": 4294.13, "Id": 281475035434072},
        {"Name": "jpez", "Planet": "naboo", "Timestamp": 1697156142820, "X": -5161.19, "Y": 4297.04, "Id": 281475035714514},
        {"Name": "tooroso", "Planet": "naboo", "Timestamp": 1698249099762, "X": -4827.71, "Y": 3824.33, "Id": 281475035755689},
        {"Name": "robia", "Planet": "naboo", "Timestamp": 1697842063901, "X": -5163.84, "Y": 4290.47, "Id": 281475036450405},
        {"Name": "delorian kitre", "Planet": "corellia", "Timestamp": 1697203123279, "X": -66.74, "Y": -4716.33, "Id": 281475036638529},
        {"Name": "glini ehalev", "Planet": "naboo", "Timestamp": 1697334829763, "X": -4954.71, "Y": 3989.01, "Id": 281475036712116},
        {"Name": "kenshao z'wolf", "Planet": "naboo", "Timestamp": 1697301005341, "X": 5663.47, "Y": 6947.47, "Id": 281475036796875},
        {"Name": "iwuluca", "Planet": "naboo", "Timestamp": 1697156142820, "X": -5013.8, "Y": 4249.99, "Id": 281475037420891},
        {"Name": "ceri", "Planet": "naboo", "Timestamp": 1697502152906, "X": -5161.65, "Y": 4294.55, "Id": 281475037634137},
        {"Name": "cheetra", "Planet": "naboo", "Timestamp": 1698025378691, "X": -5212.31, "Y": 4306.86, "Id": 281475037849394},
        {"Name": "basea", "Planet": "corellia", "Timestamp": 1697587421429, "X": -62.86, "Y": -4710.43, "Id": 281475038396455},
        {"Name": "creator", "Planet": "naboo", "Timestamp": 1697419629524, "X": -5092.88, "Y": 3811.63, "Id": 281475038574585},
        {"Name": "lace bauer", "Planet": "naboo", "Timestamp": 1697302049196, "X": 5126.15, "Y": 6617.19, "Id": 281475038767412},
        {"Name": "hobi-one", "Planet": "naboo", "Timestamp": 1697156142820, "X": -5158.1, "Y": 4290.92, "Id": 281475039107891},
        {"Name": "hobi-two", "Planet": "naboo", "Timestamp": 1697156142820, "X": -5159.57, "Y": 4289.14, "Id": 281475039112532},
        {"Name": "tickle mahpickle", "Planet": "naboo", "Timestamp": 1697626848997, "X": -5160.14, "Y": 4291.86, "Id": 281475042004435},
        {"Name": "psaul duun", "Planet": "rori", "Timestamp": 1697549485253, "X": 3672.99, "Y": -6410.48, "Id": 281475042849114},
        {"Name": "visigoth", "Planet": "naboo", "Timestamp": 1697156142820, "X": -5162.03, "Y": 4287.99, "Id": 281475042916235},
        {"Name": "lez lez", "Planet": "dantooine", "Timestamp": 1697534493205, "X": 1042.55, "Y": -685.52, "Id": 281475043280127},
        {"Name": "wendigochabella", "Planet": "naboo", "Timestamp": 1697419625167, "X": -5170.91, "Y": 3787.34, "Id": 281475043504890},
        {"Name": "eve ning", "Planet": "naboo", "Timestamp": 1697681614475, "X": -5160.33, "Y": 4285.43, "Id": 281475043692626},
        {"Name": "valentine", "Planet": "naboo", "Timestamp": 1697842067741, "X": -5158.66, "Y": 4290.14, "Id": 281475044348645},
        {"Name": "slingblade", "Planet": "naboo", "Timestamp": 1697586828373, "X": -4855.84, "Y": 4150.6, "Id": 281475044361440},
        {"Name": "frog", "Planet": "naboo", "Timestamp": 1697280151122, "X": -5163.82, "Y": 4291.27, "Id": 281475044364428},
        {"Name": "petra", "Planet": "naboo", "Timestamp": 1697242983412, "X": -4865.98, "Y": 4183.42, "Id": 281475044507611},
        {"Name": "watch", "Planet": "dantooine", "Timestamp": 1697833615307, "X": 6309.01, "Y": -4169.15, "Id": 281475044631091},
        {"Name": "listen", "Planet": "dantooine", "Timestamp": 1697833615307, "X": 6307.32, "Y": -4169.27, "Id": 281475044637916},
        {"Name": "warmaker", "Planet": "naboo", "Timestamp": 1697670266698, "X": -5158.28, "Y": 4292.51, "Id": 281475044992933},
        {"Name": "stallone ahazi", "Planet": "naboo", "Timestamp": 1697640152506, "X": -5161.18, "Y": 4293.07, "Id": 281475045164607},
        {"Name": "tttt", "Planet": "naboo", "Timestamp": 1697290463876, "X": -5160.3, "Y": 4292.81, "Id": 281475045896885},
        {"Name": "deb", "Planet": "naboo", "Timestamp": 1697585560997, "X": -5167.1, "Y": 4289.92, "Id": 281475045986262},
        {"Name": "pedro", "Planet": "corellia", "Timestamp": 1697203867612, "X": -70.68, "Y": -4706.78, "Id": 281475046008376},
        {"Name": "earthwormjim", "Planet": "naboo", "Timestamp": 1697408601218, "X": -5009.77, "Y": 4197.98, "Id": 281475046089837},
        {"Name": "iaxemo", "Planet": "naboo", "Timestamp": 1697571313324, "X": -5160.6, "Y": 4293.81, "Id": 281475046282646},
        {"Name": "kraken", "Planet": "naboo", "Timestamp": 1697293603035, "X": -5162.25, "Y": 4292.5, "Id": 281475046368140},
        {"Name": "bones mccoy", "Planet": "corellia", "Timestamp": 1697204073796, "X": -64.01, "Y": -4706.0, "Id": 281475046389067},
        {"Name": "jimmy", "Planet": "naboo", "Timestamp": 1697293578451, "X": -4851.97, "Y": 4061.77, "Id": 281475046421947},
        {"Name": "lawlerskates", "Planet": "naboo", "Timestamp": 1697536790551, "X": -4819.68, "Y": 4168.56, "Id": 281475046990421},
        {"Name": "cisco", "Planet": "endor", "Timestamp": 1697938434629, "X": -954.32, "Y": 1554.85, "Id": 281475047105683},
        {"Name": "maniti", "Planet": "naboo", "Timestamp": 1697640527765, "X": -4957.3, "Y": 4120.41, "Id": 281475047341687},
        {"Name": "fishy", "Planet": "dantooine", "Timestamp": 1698363020619, "X": 1946.41, "Y": -1635.99, "Id": 281475047362072},
        {"Name": "manite", "Planet": "naboo", "Timestamp": 1697586774708, "X": -5503.88, "Y": 4052.69, "Id": 281475047381351},
        {"Name": "maldor", "Planet": "naboo", "Timestamp": 1698149443035, "X": -5163.17, "Y": 4282.23, "Id": 281475047440291},
        {"Name": "slacka kaos", "Planet": "naboo", "Timestamp": 1697408185361, "X": -5163.13, "Y": 4287.01, "Id": 281475047442706},
        {"Name": "manito", "Planet": "naboo", "Timestamp": 1697640625769, "X": -4949.56, "Y": 4124.45, "Id": 281475047458210},
        {"Name": "snokho", "Planet": "naboo", "Timestamp": 1697585561200, "X": -5161.86, "Y": 4291.57, "Id": 281475047691095},
        {"Name": "slacki kaos", "Planet": "naboo", "Timestamp": 1697408185418, "X": -5165.97, "Y": 4287.0, "Id": 281475047938352},
        {"Name": "grakazza", "Planet": "naboo", "Timestamp": 1697156142820, "X": -5168.13, "Y": 4286.58, "Id": 281475048136307},
        {"Name": "primo", "Planet": "naboo", "Timestamp": 1697502040392, "X": -5030.18, "Y": 4173.52, "Id": 281475048405300},
        {"Name": "slacko kaos", "Planet": "lok", "Timestamp": 1697313348464, "X": 479.4, "Y": 5514.92, "Id": 281475048557115},
        {"Name": "bea", "Planet": "dantooine", "Timestamp": 1698250112786, "X": 1987.84, "Y": -1644.94, "Id": 281475048584664},
        {"Name": "jon smith", "Planet": "dantooine", "Timestamp": 1697534493204, "X": 1038.45, "Y": -676.85, "Id": 281475049147540},
        {"Name": "bodar", "Planet": "corellia", "Timestamp": 1697198896833, "X": -67.97, "Y": -4707.51, "Id": 281475049372724},
        {"Name": "pig", "Planet": "naboo", "Timestamp": 1697418598412, "X": -4997.51, "Y": 4156.82, "Id": 281475049430481},
        {"Name": "lookingfor yourmomsnumber", "Planet": "naboo", "Timestamp": 1697502152906, "X": -5130.86, "Y": 4257.76, "Id": 281475049444444},
        {"Name": "cliff jetslam", "Planet": "naboo", "Timestamp": 1697571374532, "X": -5162.78, "Y": 4294.39, "Id": 281475049644851},
        {"Name": "dunning kruger", "Planet": "naboo", "Timestamp": 1697308631326, "X": 5280.09, "Y": 6684.05, "Id": 281475049978007},
        {"Name": "gertrude applebottom", "Planet": "naboo", "Timestamp": 1698229087262, "X": -4918.57, "Y": 4141.87, "Id": 281475049987551},
        {"Name": "yota", "Planet": "naboo", "Timestamp": 1697205104409, "X": -5023.62, "Y": 4175.72, "Id": 281475050009942},
        {"Name": "blazin", "Planet": "naboo", "Timestamp": 1697156142820, "X": -5167.76, "Y": 4289.14, "Id": 281475050065759},
        {"Name": "achillies", "Planet": "naboo", "Timestamp": 1697536810801, "X": -4788.86, "Y": 3988.31, "Id": 281475050109739},
        {"Name": "tongo creed", "Planet": "corellia", "Timestamp": 1697196365866, "X": -70.09, "Y": -4713.54, "Id": 281475050169555},
        {"Name": "cantina band", "Planet": "naboo", "Timestamp": 1697156142820, "X": -5185.63, "Y": 4265.07, "Id": 281475050170181},
        {"Name": "mandingo", "Planet": "corellia", "Timestamp": 1698278846775, "X": -3382.25, "Y": 3539.81, "Id": 281475050350664},
        {"Name": "cantinas furry", "Planet": "naboo", "Timestamp": 1697419796972, "X": -5766.21, "Y": 4237.33, "Id": 281475050375725},
        {"Name": "barris jodo", "Planet": "corellia", "Timestamp": 1697197259910, "X": -71.93, "Y": -4714.38, "Id": 281475050427054},
        {"Name": "dell laptop", "Planet": "naboo", "Timestamp": 1697419725808, "X": -4967.05, "Y": 3782.66, "Id": 281475050544752},
        {"Name": "krayt killer", "Planet": "naboo", "Timestamp": 1697463459295, "X": -5124.88, "Y": 4169.69, "Id": 281475050574603},
        {"Name": "molly", "Planet": "naboo", "Timestamp": 1697408185762, "X": -5161.2, "Y": 4296.63, "Id": 281475050997914},
        {"Name": "raymus antilles", "Planet": "naboo", "Timestamp": 1697156142820, "X": -5157.75, "Y": 4283.25, "Id": 281475051038930},
        {"Name": "spudzzz", "Planet": "naboo", "Timestamp": 1697334499534, "X": -5004.81, "Y": 4156.21, "Id": 281475051069867},
        {"Name": "krunky tooturnt", "Planet": "naboo", "Timestamp": 1697629759069, "X": 5283.55, "Y": 6691.76, "Id": 281475051476070},
        {"Name": "dru mccarty", "Planet": "naboo", "Timestamp": 1697206919794, "X": -4747.01, "Y": 3325.12, "Id": 281475051652390},
        {"Name": "naki", "Planet": "naboo", "Timestamp": 1697156142820, "X": -5163.92, "Y": 4295.77, "Id": 281475051666795},
        {"Name": "ioni", "Planet": "naboo", "Timestamp": 1697156142820, "X": -5165.12, "Y": 4294.95, "Id": 281475051677003},
        {"Name": "cyclone'jack", "Planet": "naboo", "Timestamp": 1697858735546, "X": -4840.35, "Y": 4181.02, "Id": 281475051693242},
        {"Name": "alex mopy", "Planet": "corellia", "Timestamp": 1698350775060, "X": -135.68, "Y": -4722.45, "Id": 281475051831821},
        {"Name": "chappy", "Planet": "dantooine", "Timestamp": 1697534493205, "X": 1039.35, "Y": -654.73, "Id": 281475051951709},
        {"Name": "clappy", "Planet": "naboo", "Timestamp": 1697502152906, "X": -5165.66, "Y": 4288.71, "Id": 281475051984600},
        {"Name": "terry crews", "Planet": "naboo", "Timestamp": 1697242983413, "X": -4974.64, "Y": 4234.43, "Id": 281475052136887},
        {"Name": "unclerico", "Planet": "naboo", "Timestamp": 1697280151325, "X": -5162.11, "Y": 4295.78, "Id": 281475052278651},
        {"Name": "iraaxixi arubohorowi", "Planet": "naboo", "Timestamp": 1697408186005, "X": -5165.87, "Y": 4292.47, "Id": 281475052652654},
        {"Name": "rambus", "Planet": "naboo", "Timestamp": 1697280116989, "X": -4871.4, "Y": 4174.69, "Id": 281475053225151},
        {"Name": "diggem dafrawg", "Planet": "corellia", "Timestamp": 1698350775060, "X": -146.31, "Y": -4722.43, "Id": 281475053573580},
        {"Name": "vakeshi", "Planet": "naboo", "Timestamp": 1697647607200, "X": -4853.56, "Y": 4171.02, "Id": 281475053794560},
        {"Name": "strange", "Planet": "naboo", "Timestamp": 1698025375516, "X": -5162.28, "Y": 4282.2, "Id": 281475054096471},
        {"Name": "shwing", "Planet": "naboo", "Timestamp": 1698249106658, "X": -4888.32, "Y": 3914.64, "Id": 281475054124344},
        {"Name": "kek", "Planet": "naboo", "Timestamp": 1697156142820, "X": -5167.96, "Y": 4289.25, "Id": 281475054265499},
        {"Name": "sleven", "Planet": "naboo", "Timestamp": 1697205104409, "X": -4865.38, "Y": 4167.2, "Id": 281475054542469},
        {"Name": "hilaria moriarthy", "Planet": "naboo", "Timestamp": 1697907646673, "X": -5160.79, "Y": 4292.09, "Id": 281475054600842},
        {"Name": "nuud elboy", "Planet": "dantooine", "Timestamp": 1697534493205, "X": 1065.24, "Y": -710.71, "Id": 281475055136782},
        {"Name": "winston", "Planet": "naboo", "Timestamp": 1697537470697, "X": -5161.81, "Y": 4278.8, "Id": 281475055149590},
        {"Name": "liara", "Planet": "naboo", "Timestamp": 1697242983413, "X": -4849.77, "Y": 4138.83, "Id": 281475055152996},
        {"Name": "juuno callisto", "Planet": "naboo", "Timestamp": 1697280116989, "X": -4982.24, "Y": 4211.27, "Id": 281475055191724},
        {"Name": "ent", "Planet": "naboo", "Timestamp": 1697408186005, "X": -5162.69, "Y": 4297.12, "Id": 281475055265830},
        {"Name": "slaying mango", "Planet": "naboo", "Timestamp": 1697458964142, "X": -5003.02, "Y": 4215.54, "Id": 281475055562727},
        {"Name": "muawijhe sky", "Planet": "naboo", "Timestamp": 1697293578451, "X": -4943.81, "Y": 4130.7, "Id": 281475055953061},
        {"Name": "xonox", "Planet": "naboo", "Timestamp": 1698249099762, "X": -4829.11, "Y": 3823.43, "Id": 281475056217824},
        {"Name": "terric trim", "Planet": "naboo", "Timestamp": 1697640195388, "X": 5119.35, "Y": 6620.47, "Id": 281475056345980},
        {"Name": "smirkna thellere", "Planet": "naboo", "Timestamp": 1697644869217, "X": -4818.27, "Y": 4091.16, "Id": 281475056359062},
        {"Name": "father grigori", "Planet": "corellia", "Timestamp": 1698350775059, "X": -134.92, "Y": -4721.56, "Id": 281475056518723},
        {"Name": "reajo", "Planet": "naboo", "Timestamp": 1698249099762, "X": -4828.5, "Y": 3825.28, "Id": 281475056617996},
        {"Name": "void warranty", "Planet": "naboo", "Timestamp": 1698249106658, "X": -4887.2, "Y": 3914.56, "Id": 281475056628429},
        {"Name": "mog", "Planet": "naboo", "Timestamp": 1697408186005, "X": -5167.29, "Y": 4288.64, "Id": 281475056973700},
        {"Name": "tago", "Planet": "naboo", "Timestamp": 1697408186005, "X": -5167.42, "Y": 4290.91, "Id": 281475056987516},
        {"Name": "veolia netherlands", "Planet": "naboo", "Timestamp": 1697897069029, "X": -4877.65, "Y": 4028.28, "Id": 281475056996484},
        {"Name": "vektar", "Planet": "naboo", "Timestamp": 1697640137665, "X": -4908.99, "Y": 4028.1, "Id": 281475057321445},
        {"Name": "tago", "Planet": "naboo", "Timestamp": 1697463729501, "X": -4856.0, "Y": 4162.0, "Id": 281475057876431},
        {"Name": "king leonidas", "Planet": "naboo", "Timestamp": 1698356569409, "X": -4867.83, "Y": 3831.16, "Id": 281475058186791},
        {"Name": "goat", "Planet": "naboo", "Timestamp": 1697586772803, "X": -5506.69, "Y": 4060.81, "Id": 281475058528068},
        {"Name": "slacks kaos", "Planet": "naboo", "Timestamp": 1697534069574, "X": -4967.5, "Y": 4077.75, "Id": 281475058537409},
        {"Name": "jim", "Planet": "naboo", "Timestamp": 1697585539777, "X": -4856.0, "Y": 4162.0, "Id": 281475059044299},
        {"Name": "o'tana mor", "Planet": "naboo", "Timestamp": 1697657978221, "X": -5166.29, "Y": 4288.08, "Id": 281475059171776},
        {"Name": "drake", "Planet": "naboo", "Timestamp": 1697657978221, "X": -5161.02, "Y": 4296.32, "Id": 281475059211453},
        {"Name": "zigno aowip", "Planet": "naboo", "Timestamp": 1698086119576, "X": -4941.7, "Y": 3645.61, "Id": 281475059701872},
        {"Name": "vissna", "Planet": "naboo", "Timestamp": 1697896751239, "X": -5172.65, "Y": 4285.08, "Id": 281475061046061},
        {"Name": "bazari", "Planet": "naboo", "Timestamp": 1697833383493, "X": -4879.24, "Y": 4177.0, "Id": 281475061258694},
        {"Name": "goat", "Planet": "naboo", "Timestamp": 1697871624780, "X": -4838.79, "Y": 4158.71, "Id": 281475061585651},
        {"Name": "enki", "Planet": "dantooine", "Timestamp": 1698097172509, "X": 1062.47, "Y": -709.36, "Id": 281475061643556},
        {"Name": "veo netherlands", "Planet": "naboo", "Timestamp": 1697896750957, "X": -5163.05, "Y": 4292.62, "Id": 281475061780497},
        {"Name": "lizard buffs", "Planet": "naboo", "Timestamp": 1698013750884, "X": -5167.13, "Y": 4281.48, "Id": 281475061876986},
        {"Name": "isabo moriarthy", "Planet": "naboo", "Timestamp": 1697907647032, "X": -5161.51, "Y": 4289.74, "Id": 281475061906475},
        {"Name": "elo", "Planet": "naboo", "Timestamp": 1698086152617, "X": -5163.11, "Y": 4145.2, "Id": 281475062049503},
        {"Name": "zoledronic infusion", "Planet": "naboo", "Timestamp": 1697980109417, "X": -5163.71, "Y": 4288.82, "Id": 281475062288196},
        {"Name": "hunter bowman", "Planet": "naboo", "Timestamp": 1697980107389, "X": -5070.73, "Y": 4052.47, "Id": 281475062680517},
        {"Name": "defense", "Planet": "dantooine", "Timestamp": 1698070757630, "X": -622.36, "Y": 2553.19, "Id": 281475062801920},
        {"Name": "offense", "Planet": "dantooine", "Timestamp": 1698106721353, "X": -631.96, "Y": 2541.91, "Id": 281475062834049},
        {"Name": "eyecandy", "Planet": "naboo", "Timestamp": 1698059252696, "X": -5162.89, "Y": 4289.29, "Id": 281475063032718},
        {"Name": "dizzy lizzie", "Planet": "naboo", "Timestamp": 1698059252696, "X": -5158.73, "Y": 4283.41, "Id": 281475063361457},
        {"Name": "slackie kaos", "Planet": "naboo", "Timestamp": 1698080701989, "X": -5163.76, "Y": 4288.21, "Id": 281475063497108},
        {"Name": "thirdtimes charm", "Planet": "naboo", "Timestamp": 1698107485966, "X": -5163.63, "Y": 4294.35, "Id": 281475063842313},
        {"Name": "stevie", "Planet": "naboo", "Timestamp": 1698246405964, "X": -5160.7, "Y": 4291.84, "Id": 281475064872156},
        {"Name": "mind buffa", "Planet": "dantooine", "Timestamp": 1698249254640, "X": -631.1, "Y": 2508.13, "Id": 281475065108016},
        {"Name": "juicemasta jay", "Planet": "naboo", "Timestamp": 1698246407762, "X": -5163.63, "Y": 4293.65, "Id": 281475065120738},
        {"Name": "yuso hungry", "Planet": "dantooine", "Timestamp": 1698252291081, "X": -2987.0, "Y": -2226.0, "Id": 281475065217567},
        {"Name": "mack", "Planet": "naboo", "Timestamp": 1698356550428, "X": -5013.13, "Y": 4249.3, "Id": 281475065958110},
    ],
}
